requirements_checker/__init__.py
requirements_checker/check_pkg.py
requirements_checker/check_string.py
requirements_checker/check_version.py
requirements_checker-0.2.18.dist-info/LICENSE
requirements_checker-0.2.18.dist-info/METADATA
requirements_checker-0.2.18.dist-info/WHEEL
requirements_checker-0.2.18.dist-info/top_level.txt
requirements_checker-0.2.18.dist-info/RECORD
